ibproxy/__init__.py
ibproxy/const.py
ibproxy/main.py
ibproxy/models.py
ibproxy/rate.py
ibproxy/status.py
ibproxy/tickle.py
ibproxy/uptime.py
ibproxy/util.py
ibproxy/logging/handlers.py
ibproxy/middleware/__init__.py
ibproxy/middleware/request_id.py
ibproxy-0.1.3.dist-info/licenses/LICENSE.md
ibproxy-0.1.3.dist-info/METADATA
ibproxy-0.1.3.dist-info/WHEEL
ibproxy-0.1.3.dist-info/entry_points.txt
ibproxy-0.1.3.dist-info/top_level.txt
ibproxy-0.1.3.dist-info/RECORD
