Metadata-Version: 2.4
Name: ibproxy
Version: 0.1.3
Summary: A proxy service for the Interactive Brokers API
Author: Andrew Collier
Maintainer: Andrew Collier
Requires-Python: >=3.12
License-File: LICENSE.md
Requires-Dist: fastapi>=0.119.0
Requires-Dist: uvicorn>=0.37.0
Requires-Dist: ibauth>=0.1.1
Requires-Dist: httpx>=0.28.1
Requires-Dist: curlify2>=2.0.0
Requires-Dist: bs4>=0.0.2
Requires-Dist: pydantic>=2.11.10
Dynamic: license-file
